merlin/__init__.py
merlin/cfg.py
merlin/chipmunk.py
merlin/chips.py
merlin/dates.py
merlin/files.py
merlin/formats.py
merlin/functions.py
merlin/geometry.py
merlin/rods.py
merlin/specs.py
test/__init__.py
test/test___init__.py
test/test_chipmunk.py
test/test_chips.py
test/test_dates.py
test/test_files.py
test/test_formats.py
test/test_functions.py
test/test_geometry.py
test/test_rods.py
test/test_specs.py
lcmap_merlin-2.3.3.1.dist-info/LICENSE
lcmap_merlin-2.3.3.1.dist-info/METADATA
lcmap_merlin-2.3.3.1.dist-info/WHEEL
lcmap_merlin-2.3.3.1.dist-info/top_level.txt
lcmap_merlin-2.3.3.1.dist-info/RECORD
