Metadata-Version: 2.1
Name: lcmap-merlin
Version: 2.3.3.1
Summary: Python client library for LCMAP rasters
Home-page: http://github.com/usgs-eros/lcmap-merlin
Author: USGS EROS LCMAP
Author-email: 
License: Unlicense
Keywords: usgs lcmap eros
Platform: UNKNOWN
Classifier: Development Status :: 5 - Production/Stable
Classifier: License :: Public Domain
Classifier: Programming Language :: Python :: 3.6
Requires-Dist: cytoolz
Requires-Dist: numpy
Requires-Dist: requests
Requires-Dist: python-dateutil
Provides-Extra: dev
Requires-Dist: twine ; extra == 'dev'
Provides-Extra: doc
Requires-Dist: sphinx ; extra == 'doc'
Requires-Dist: sphinx-autobuild ; extra == 'doc'
Requires-Dist: sphinx-rtd-theme ; extra == 'doc'
Provides-Extra: test
Requires-Dist: pytest ; extra == 'test'
Requires-Dist: pytest-cov ; extra == 'test'
Requires-Dist: hypothesis ; extra == 'test'
Requires-Dist: vcrpy ; extra == 'test'
